pybsn/__init__.py
pybsn-0.4.2.data/scripts/pybsn-repl
pybsn-0.4.2.data/scripts/pybsn-schema
pybsn-0.4.2.dist-info/licenses/LICENSE
pybsn-0.4.2.dist-info/METADATA
pybsn-0.4.2.dist-info/WHEEL
pybsn-0.4.2.dist-info/top_level.txt
pybsn-0.4.2.dist-info/RECORD
